detectron2/_C.cp37-win_amd64.pyd
detectron2/__init__.py
detectron2/checkpoint/__init__.py
detectron2/checkpoint/c2_model_loading.py
detectron2/checkpoint/catalog.py
detectron2/checkpoint/detection_checkpoint.py
detectron2/config/__init__.py
detectron2/config/compat.py
detectron2/config/config.py
detectron2/config/defaults.py
detectron2/config/instantiate.py
detectron2/config/lazy.py
detectron2/data/__init__.py
detectron2/data/build.py
detectron2/data/catalog.py
detectron2/data/common.py
detectron2/data/dataset_mapper.py
detectron2/data/detection_utils.py
detectron2/data/datasets/__init__.py
detectron2/data/datasets/builtin.py
detectron2/data/datasets/builtin_meta.py
detectron2/data/datasets/cityscapes.py
detectron2/data/datasets/cityscapes_panoptic.py
detectron2/data/datasets/coco.py
detectron2/data/datasets/coco_panoptic.py
detectron2/data/datasets/lvis.py
detectron2/data/datasets/lvis_v0_5_categories.py
detectron2/data/datasets/lvis_v1_categories.py
detectron2/data/datasets/pascal_voc.py
detectron2/data/datasets/register_coco.py
detectron2/data/samplers/__init__.py
detectron2/data/samplers/distributed_sampler.py
detectron2/data/samplers/grouped_batch_sampler.py
detectron2/data/transforms/__init__.py
detectron2/data/transforms/augmentation.py
detectron2/data/transforms/augmentation_impl.py
detectron2/data/transforms/transform.py
detectron2/engine/__init__.py
detectron2/engine/defaults.py
detectron2/engine/hooks.py
detectron2/engine/launch.py
detectron2/engine/train_loop.py
detectron2/evaluation/__init__.py
detectron2/evaluation/cityscapes_evaluation.py
detectron2/evaluation/coco_evaluation.py
detectron2/evaluation/evaluator.py
detectron2/evaluation/fast_eval_api.py
detectron2/evaluation/lvis_evaluation.py
detectron2/evaluation/panoptic_evaluation.py
detectron2/evaluation/pascal_voc_evaluation.py
detectron2/evaluation/rotated_coco_evaluation.py
detectron2/evaluation/sem_seg_evaluation.py
detectron2/evaluation/testing.py
detectron2/export/__init__.py
geoai_detectron2-0.4.dist-info/LICENSE
geoai_detectron2-0.4.dist-info/METADATA
geoai_detectron2-0.4.dist-info/WHEEL
geoai_detectron2-0.4.dist-info/top_level.txt
geoai_detectron2-0.4.dist-info/RECORD
