Metadata-Version: 2.1
Name: geoai-detectron2
Version: 0.4
Summary: Detectron2 is FAIR's next-generation research platform for object detection and segmentation.
Home-page: https://github.com/facebookresearch/detectron2
Author: FAIR
License: UNKNOWN
Platform: UNKNOWN
Requires-Python: >=3.6
Requires-Dist: termcolor (>=1.1)
Requires-Dist: Pillow (>=7.1)
Requires-Dist: yacs (>=0.1.6)
Requires-Dist: tabulate
Requires-Dist: cloudpickle
Requires-Dist: matplotlib
Requires-Dist: tqdm (>4.29.0)
Requires-Dist: tensorboard
Requires-Dist: fvcore (<0.1.6,>=0.1.5)
Requires-Dist: iopath (<0.1.9,>=0.1.7)
Requires-Dist: pycocotools (>=2.0.2)
Requires-Dist: future
Requires-Dist: pydot
Requires-Dist: omegaconf (>=2.1.0rc1)
Requires-Dist: hydra-core (>=1.1.0rc1)
Requires-Dist: black (==21.4b2)
Requires-Dist: dataclasses ; python_version < "3.7"
Provides-Extra: all
Requires-Dist: shapely ; extra == 'all'
Requires-Dist: pygments (>=2.2) ; extra == 'all'
Requires-Dist: psutil ; extra == 'all'
Provides-Extra: dev
Requires-Dist: flake8 (==3.8.1) ; extra == 'dev'
Requires-Dist: isort (==4.3.21) ; extra == 'dev'
Requires-Dist: flake8-bugbear ; extra == 'dev'
Requires-Dist: flake8-comprehensions ; extra == 'dev'
